Metadata-Version: 2.4
Name: gyselle_image_processing
Version: 0.0.1
Summary: Image Processing Package using Skimage
Home-page: https://github.com/gyselle-marques/image-processing-package
Author: Gyselle_Marques
Author-email: gmsilva619@gmail.com
Requires-Python: >=3.5
Requires-Dist: matplotlib
Requires-Dist: numpy
Requires-Dist: scikit-image>=0.16.1
Dynamic: author
Dynamic: author-email
Dynamic: description
Dynamic: description-content-type
Dynamic: home-page
Dynamic: requires-dist
Dynamic: requires-python
Dynamic: summary
